{
  "seatflowLayoutVersion": "v12.8",
  "exportedAt": "2026-06-12T18:40:00.141Z",
  "layout": {
    "id": "layout-ftyqadm7",
    "name": "仁保教室",
    "facilityType": "juku",
    "floor": {
      "w": 1120,
      "h": 720,
      "grid": 20
    },
    "outline": [],
    "draftOutline": [],
    "items": [
      {
        "id": "item-sgak8xyo",
        "type": "room",
        "label": "講師ルーム",
        "x": 10,
        "y": 565,
        "w": 220,
        "h": 140,
        "r": 0,
        "status": "free",
        "assignedName": "",
        "note": "",
        "locked": false,
        "assignable": false,
        "assignableLocked": false,
        "color": "",
        "z": 1,
        "fontSize": 13,
        "textVertical": false,
        "noBorder": false,
        "groupId": null
      },
      {
        "id": "item-2d6vgxx0",
        "type": "meeting",
        "label": "面談室",
        "x": 885,
        "y": 572,
        "w": 220,
        "h": 128,
        "r": 0,
        "status": "free",
        "assignedName": "",
        "note": "",
        "locked": false,
        "assignable": false,
        "assignableLocked": false,
        "color": "#fce7f3",
        "z": 2,
        "fontSize": 13,
        "textVertical": false,
        "noBorder": false,
        "groupId": null
      },
      {
        "id": "item-9fbirzyz",
        "type": "door",
        "label": "入口",
        "x": 415,
        "y": 662,
        "w": 290,
        "h": 38,
        "r": 0,
        "status": "free",
        "assignedName": "",
        "note": "",
        "locked": false,
        "assignable": false,
        "assignableLocked": false,
        "color": "",
        "z": 3,
        "fontSize": 13,
        "textVertical": false,
        "noBorder": false,
        "groupId": null
      },
      {
        "id": "item-049dkbug",
        "type": "table",
        "label": "",
        "x": 750,
        "y": 400,
        "w": 80,
        "h": 80,
        "r": 0,
        "status": "free",
        "assignedName": "",
        "note": "",
        "locked": false,
        "assignable": false,
        "assignableLocked": false,
        "color": "",
        "z": 4,
        "fontSize": 13,
        "textVertical": false,
        "noBorder": false,
        "groupId": null
      },
      {
        "id": "item-3oa9hko3",
        "type": "seat",
        "label": "",
        "x": 490,
        "y": 135,
        "w": 80,
        "h": 60,
        "r": 0,
        "status": "free",
        "assignedName": "",
        "note": "",
        "locked": false,
        "assignable": true,
        "assignableLocked": true,
        "color": "",
        "z": 5,
        "fontSize": 13,
        "textVertical": false,
        "noBorder": false,
        "groupId": null
      },
      {
        "id": "item-5ou75ltp",
        "type": "seat",
        "label": "4",
        "x": 645,
        "y": 135,
        "w": 80,
        "h": 60,
        "r": 0,
        "status": "free",
        "assignedName": "",
        "note": "",
        "locked": false,
        "assignable": true,
        "assignableLocked": true,
        "color": "",
        "z": 6,
        "fontSize": 13,
        "textVertical": false,
        "noBorder": false,
        "groupId": null
      },
      {
        "id": "item-uy2f83mb",
        "type": "seat",
        "label": "8",
        "x": 750,
        "y": 135,
        "w": 80,
        "h": 60,
        "r": 0,
        "status": "free",
        "assignedName": "",
        "note": "",
        "locked": false,
        "assignable": true,
        "assignableLocked": true,
        "color": "",
        "z": 7,
        "fontSize": 13,
        "textVertical": false,
        "noBorder": false,
        "groupId": null
      },
      {
        "id": "item-wtj0mqew",
        "type": "seat",
        "label": "13",
        "x": 900,
        "y": 135,
        "w": 80,
        "h": 60,
        "r": 0,
        "status": "used",
        "assignedName": "川岡哲也",
        "note": "",
        "locked": false,
        "assignable": true,
        "assignableLocked": true,
        "color": "",
        "z": 8,
        "fontSize": 13,
        "textVertical": false,
        "noBorder": false,
        "groupId": null,
        "personId": "person-9wbn38wh"
      },
      {
        "id": "item-96qt7f1s",
        "type": "seat",
        "label": "18",
        "x": 1010,
        "y": 135,
        "w": 80,
        "h": 60,
        "r": 0,
        "status": "free",
        "assignedName": "",
        "note": "",
        "locked": false,
        "assignable": true,
        "assignableLocked": true,
        "color": "",
        "z": 9,
        "fontSize": 13,
        "textVertical": false,
        "noBorder": false,
        "groupId": null,
        "personId": ""
      },
      {
        "id": "item-7jtmcveg",
        "type": "seat",
        "label": "",
        "x": 490,
        "y": 200,
        "w": 80,
        "h": 60,
        "r": 0,
        "status": "free",
        "assignedName": "",
        "note": "",
        "locked": false,
        "assignable": true,
        "assignableLocked": true,
        "color": "",
        "z": 10,
        "fontSize": 13,
        "textVertical": false,
        "noBorder": false,
        "groupId": null
      },
      {
        "id": "item-bp7wmpv4",
        "type": "seat",
        "label": "3",
        "x": 645,
        "y": 200,
        "w": 80,
        "h": 60,
        "r": 0,
        "status": "free",
        "assignedName": "",
        "note": "",
        "locked": false,
        "assignable": true,
        "assignableLocked": true,
        "color": "",
        "z": 11,
        "fontSize": 13,
        "textVertical": false,
        "noBorder": false,
        "groupId": null
      },
      {
        "id": "item-cy6fklmc",
        "type": "seat",
        "label": "7",
        "x": 750,
        "y": 200,
        "w": 80,
        "h": 60,
        "r": 0,
        "status": "free",
        "assignedName": "",
        "note": "",
        "locked": false,
        "assignable": true,
        "assignableLocked": true,
        "color": "",
        "z": 12,
        "fontSize": 13,
        "textVertical": false,
        "noBorder": false,
        "groupId": null
      },
      {
        "id": "item-nei04knm",
        "type": "seat",
        "label": "12",
        "x": 900,
        "y": 200,
        "w": 80,
        "h": 60,
        "r": 0,
        "status": "free",
        "assignedName": "",
        "note": "",
        "locked": false,
        "assignable": true,
        "assignableLocked": true,
        "color": "",
        "z": 13,
        "fontSize": 13,
        "textVertical": false,
        "noBorder": false,
        "groupId": null,
        "personId": ""
      },
      {
        "id": "item-7uhqot3t",
        "type": "seat",
        "label": "17",
        "x": 1010,
        "y": 200,
        "w": 80,
        "h": 60,
        "r": 0,
        "status": "free",
        "assignedName": "",
        "note": "",
        "locked": false,
        "assignable": true,
        "assignableLocked": true,
        "color": "",
        "z": 14,
        "fontSize": 13,
        "textVertical": false,
        "noBorder": false,
        "groupId": null,
        "personId": ""
      },
      {
        "id": "item-e7j2hnna",
        "type": "seat",
        "label": "",
        "x": 490,
        "y": 265,
        "w": 80,
        "h": 60,
        "r": 0,
        "status": "free",
        "assignedName": "",
        "note": "",
        "locked": false,
        "assignable": true,
        "assignableLocked": true,
        "color": "",
        "z": 15,
        "fontSize": 13,
        "textVertical": false,
        "noBorder": false,
        "groupId": null
      },
      {
        "id": "item-2dw0qcc4",
        "type": "seat",
        "label": "2",
        "x": 645,
        "y": 265,
        "w": 80,
        "h": 60,
        "r": 0,
        "status": "free",
        "assignedName": "",
        "note": "",
        "locked": false,
        "assignable": true,
        "assignableLocked": true,
        "color": "",
        "z": 16,
        "fontSize": 13,
        "textVertical": false,
        "noBorder": false,
        "groupId": null
      },
      {
        "id": "item-99rd6mcb",
        "type": "seat",
        "label": "6",
        "x": 750,
        "y": 265,
        "w": 80,
        "h": 60,
        "r": 0,
        "status": "free",
        "assignedName": "",
        "note": "",
        "locked": false,
        "assignable": true,
        "assignableLocked": true,
        "color": "",
        "z": 17,
        "fontSize": 13,
        "textVertical": false,
        "noBorder": false,
        "groupId": null
      },
      {
        "id": "item-yxkfdmk1",
        "type": "seat",
        "label": "11",
        "x": 900,
        "y": 265,
        "w": 80,
        "h": 60,
        "r": 0,
        "status": "free",
        "assignedName": "",
        "note": "",
        "locked": false,
        "assignable": true,
        "assignableLocked": true,
        "color": "",
        "z": 18,
        "fontSize": 13,
        "textVertical": false,
        "noBorder": false,
        "groupId": null,
        "personId": ""
      },
      {
        "id": "item-4q52laad",
        "type": "seat",
        "label": "16",
        "x": 1010,
        "y": 265,
        "w": 80,
        "h": 60,
        "r": 0,
        "status": "free",
        "assignedName": "",
        "note": "",
        "locked": false,
        "assignable": true,
        "assignableLocked": true,
        "color": "",
        "z": 19,
        "fontSize": 13,
        "textVertical": false,
        "noBorder": false,
        "groupId": null,
        "personId": ""
      },
      {
        "id": "item-sy5xvudx",
        "type": "seat",
        "label": "",
        "x": 490,
        "y": 330,
        "w": 80,
        "h": 60,
        "r": 0,
        "status": "free",
        "assignedName": "",
        "note": "",
        "locked": false,
        "assignable": true,
        "assignableLocked": true,
        "color": "",
        "z": 20,
        "fontSize": 13,
        "textVertical": false,
        "noBorder": false,
        "groupId": null
      },
      {
        "id": "item-wb8gysjg",
        "type": "seat",
        "label": "1",
        "x": 645,
        "y": 330,
        "w": 80,
        "h": 60,
        "r": 0,
        "status": "free",
        "assignedName": "",
        "note": "",
        "locked": false,
        "assignable": true,
        "assignableLocked": true,
        "color": "",
        "z": 21,
        "fontSize": 13,
        "textVertical": false,
        "noBorder": false,
        "groupId": null
      },
      {
        "id": "item-w9ptwfnl",
        "type": "seat",
        "label": "5",
        "x": 750,
        "y": 330,
        "w": 80,
        "h": 60,
        "r": 0,
        "status": "free",
        "assignedName": "",
        "note": "",
        "locked": false,
        "assignable": true,
        "assignableLocked": true,
        "color": "",
        "z": 22,
        "fontSize": 13,
        "textVertical": false,
        "noBorder": false,
        "groupId": null
      },
      {
        "id": "item-v8fvlmca",
        "type": "seat",
        "label": "10",
        "x": 900,
        "y": 330,
        "w": 80,
        "h": 60,
        "r": 0,
        "status": "free",
        "assignedName": "",
        "note": "",
        "locked": false,
        "assignable": true,
        "assignableLocked": true,
        "color": "",
        "z": 23,
        "fontSize": 13,
        "textVertical": false,
        "noBorder": false,
        "groupId": null,
        "personId": ""
      },
      {
        "id": "item-tokxiakp",
        "type": "seat",
        "label": "15",
        "x": 1010,
        "y": 330,
        "w": 80,
        "h": 60,
        "r": 0,
        "status": "free",
        "assignedName": "",
        "note": "",
        "locked": false,
        "assignable": true,
        "assignableLocked": true,
        "color": "",
        "z": 24,
        "fontSize": 13,
        "textVertical": false,
        "noBorder": false,
        "groupId": null,
        "personId": ""
      },
      {
        "id": "item-uygwkik4",
        "type": "wall",
        "label": "仕切り 1",
        "x": 476,
        "y": 113,
        "w": 644,
        "h": 16,
        "r": 0,
        "status": "free",
        "assignedName": "",
        "note": "",
        "locked": false,
        "assignable": false,
        "assignableLocked": false,
        "color": "",
        "z": 25,
        "fontSize": 13,
        "textVertical": false,
        "noBorder": false,
        "groupId": null
      },
      {
        "id": "item-yfp7fttp",
        "type": "meeting",
        "label": "納戸",
        "x": 945,
        "y": 5,
        "w": 160,
        "h": 100,
        "r": 0,
        "status": "free",
        "assignedName": "",
        "note": "",
        "locked": false,
        "assignable": false,
        "assignableLocked": false,
        "color": "",
        "z": 26,
        "fontSize": 13,
        "textVertical": false,
        "noBorder": false,
        "groupId": null
      },
      {
        "id": "item-grf0wea3",
        "type": "wall",
        "label": "仕切り 1 コピー",
        "x": 300,
        "y": 7,
        "w": 16,
        "h": 475,
        "r": 0,
        "status": "free",
        "assignedName": "",
        "note": "",
        "locked": false,
        "assignable": false,
        "assignableLocked": false,
        "color": "",
        "z": 27,
        "fontSize": 13,
        "textVertical": false,
        "noBorder": false,
        "groupId": null
      },
      {
        "id": "item-ezexgit5",
        "type": "seat",
        "label": "",
        "x": 490,
        "y": 395,
        "w": 80,
        "h": 60,
        "r": 0,
        "status": "free",
        "assignedName": "",
        "note": "",
        "locked": false,
        "assignable": true,
        "assignableLocked": true,
        "color": "",
        "z": 28,
        "fontSize": 13,
        "textVertical": false,
        "noBorder": false,
        "groupId": null
      },
      {
        "id": "item-cet26vyz",
        "type": "seat",
        "label": "",
        "x": 645,
        "y": 395,
        "w": 80,
        "h": 60,
        "r": 0,
        "status": "free",
        "assignedName": "",
        "note": "",
        "locked": false,
        "assignable": true,
        "assignableLocked": true,
        "color": "",
        "z": 29,
        "fontSize": 13,
        "textVertical": false,
        "noBorder": false,
        "groupId": null
      },
      {
        "id": "item-3k7b0zoe",
        "type": "seat",
        "label": "14",
        "x": 1010,
        "y": 395,
        "w": 80,
        "h": 60,
        "r": 0,
        "status": "free",
        "assignedName": "",
        "note": "",
        "locked": false,
        "assignable": true,
        "assignableLocked": true,
        "color": "",
        "z": 30,
        "fontSize": 13,
        "textVertical": false,
        "noBorder": false,
        "groupId": null,
        "personId": ""
      },
      {
        "id": "item-z0sphjtd",
        "type": "seat",
        "label": "9",
        "x": 900,
        "y": 395,
        "w": 80,
        "h": 60,
        "r": 0,
        "status": "free",
        "assignedName": "",
        "note": "",
        "locked": false,
        "assignable": true,
        "assignableLocked": true,
        "color": "",
        "z": 31,
        "fontSize": 13,
        "textVertical": false,
        "noBorder": false,
        "groupId": null,
        "personId": ""
      },
      {
        "id": "item-0q1qura0",
        "type": "wall",
        "label": "仕切り 1 コピー コピー",
        "x": 600,
        "y": 120,
        "w": 16,
        "h": 334,
        "r": 0,
        "status": "free",
        "assignedName": "",
        "note": "",
        "locked": false,
        "assignable": false,
        "assignableLocked": false,
        "color": "",
        "z": 32,
        "fontSize": 13,
        "textVertical": false,
        "noBorder": false,
        "groupId": null
      },
      {
        "id": "item-hdgcjzv2",
        "type": "wall",
        "label": "仕切り 1 コピー コピー コピー",
        "x": 855,
        "y": 120,
        "w": 16,
        "h": 340,
        "r": 0,
        "status": "free",
        "assignedName": "",
        "note": "",
        "locked": false,
        "assignable": false,
        "assignableLocked": false,
        "color": "",
        "z": 33,
        "fontSize": 13,
        "textVertical": false,
        "noBorder": false,
        "groupId": null
      },
      {
        "id": "item-9rnugzav",
        "type": "seat",
        "label": "",
        "x": 320,
        "y": 70,
        "w": 80,
        "h": 60,
        "r": 0,
        "status": "free",
        "assignedName": "",
        "note": "",
        "locked": false,
        "assignable": true,
        "assignableLocked": true,
        "color": "",
        "z": 34,
        "fontSize": 13,
        "textVertical": false,
        "noBorder": false,
        "groupId": null
      },
      {
        "id": "item-24xm0cp3",
        "type": "seat",
        "label": "",
        "x": 320,
        "y": 135,
        "w": 80,
        "h": 60,
        "r": 0,
        "status": "free",
        "assignedName": "",
        "note": "",
        "locked": false,
        "assignable": true,
        "assignableLocked": true,
        "color": "",
        "z": 35,
        "fontSize": 13,
        "textVertical": false,
        "noBorder": false,
        "groupId": null
      },
      {
        "id": "item-zor3f2tt",
        "type": "seat",
        "label": "",
        "x": 320,
        "y": 200,
        "w": 80,
        "h": 60,
        "r": 0,
        "status": "free",
        "assignedName": "",
        "note": "",
        "locked": false,
        "assignable": true,
        "assignableLocked": true,
        "color": "",
        "z": 36,
        "fontSize": 13,
        "textVertical": false,
        "noBorder": false,
        "groupId": null
      },
      {
        "id": "item-tguhoxx9",
        "type": "seat",
        "label": "",
        "x": 320,
        "y": 265,
        "w": 80,
        "h": 60,
        "r": 0,
        "status": "free",
        "assignedName": "",
        "note": "",
        "locked": false,
        "assignable": true,
        "assignableLocked": true,
        "color": "",
        "z": 37,
        "fontSize": 13,
        "textVertical": false,
        "noBorder": false,
        "groupId": null
      },
      {
        "id": "item-6x7gqvgd",
        "type": "seat",
        "label": "",
        "x": 320,
        "y": 330,
        "w": 80,
        "h": 60,
        "r": 0,
        "status": "free",
        "assignedName": "",
        "note": "",
        "locked": false,
        "assignable": true,
        "assignableLocked": true,
        "color": "",
        "z": 38,
        "fontSize": 13,
        "textVertical": false,
        "noBorder": false,
        "groupId": null
      },
      {
        "id": "item-eslvws16",
        "type": "toilet",
        "label": "トイレ 1",
        "x": 320,
        "y": 5,
        "w": 120,
        "h": 60,
        "r": 0,
        "status": "free",
        "assignedName": "",
        "note": "",
        "locked": false,
        "assignable": false,
        "assignableLocked": false,
        "color": "#fee2e2",
        "z": 39,
        "fontSize": 13,
        "textVertical": false,
        "noBorder": false,
        "groupId": null
      },
      {
        "id": "item-693883mc",
        "type": "wall",
        "label": "仕切り 1 コピー",
        "x": 335,
        "y": 575,
        "w": 545,
        "h": 16,
        "r": 0,
        "status": "free",
        "assignedName": "",
        "note": "",
        "locked": false,
        "assignable": false,
        "assignableLocked": false,
        "color": "",
        "z": 40,
        "fontSize": 13,
        "textVertical": false,
        "noBorder": false,
        "groupId": null
      },
      {
        "id": "item-cgzcthr6",
        "type": "seat",
        "label": "",
        "x": 320,
        "y": 395,
        "w": 80,
        "h": 60,
        "r": 0,
        "status": "free",
        "assignedName": "",
        "note": "",
        "locked": false,
        "assignable": true,
        "assignableLocked": true,
        "color": "",
        "z": 41,
        "fontSize": 13,
        "textVertical": false,
        "noBorder": false,
        "groupId": null
      },
      {
        "id": "item-3b6zzlij",
        "type": "meeting",
        "label": "",
        "x": 11,
        "y": 9,
        "w": 254,
        "h": 254,
        "r": 0,
        "status": "free",
        "assignedName": "",
        "note": "",
        "locked": false,
        "assignable": false,
        "assignableLocked": false,
        "color": "",
        "z": 42,
        "fontSize": 13,
        "textVertical": false,
        "noBorder": false,
        "groupId": null
      },
      {
        "id": "item-g73a12ww",
        "type": "room",
        "label": "講師ルーム",
        "x": 15,
        "y": 308,
        "w": 133,
        "h": 257,
        "r": 0,
        "status": "free",
        "assignedName": "",
        "note": "",
        "locked": false,
        "assignable": false,
        "assignableLocked": false,
        "color": "",
        "z": 43,
        "fontSize": 13,
        "textVertical": false,
        "noBorder": false,
        "groupId": null
      },
      {
        "id": "item-ktoks7jz",
        "type": "textH",
        "label": "プロクラ",
        "x": 50,
        "y": 20,
        "w": 180,
        "h": 38,
        "r": 0,
        "status": "free",
        "assignedName": "",
        "note": "",
        "locked": false,
        "assignable": false,
        "assignableLocked": false,
        "color": "",
        "z": 44,
        "fontSize": 18,
        "textVertical": false,
        "noBorder": false,
        "groupId": null
      },
      {
        "id": "item-jiysos5i",
        "type": "wall",
        "label": "仕切り 1 コピー コピー",
        "x": 10,
        "y": 275,
        "w": 205,
        "h": 16,
        "r": 0,
        "status": "free",
        "assignedName": "",
        "note": "",
        "locked": false,
        "assignable": false,
        "assignableLocked": false,
        "color": "",
        "z": 45,
        "fontSize": 13,
        "textVertical": false,
        "noBorder": false,
        "groupId": null
      },
      {
        "id": "item-b5ml8l9j",
        "type": "door",
        "label": "受付",
        "x": 240,
        "y": 570,
        "w": 39,
        "h": 128,
        "r": 0,
        "status": "free",
        "assignedName": "",
        "note": "",
        "locked": false,
        "assignable": false,
        "assignableLocked": false,
        "color": "",
        "z": 46,
        "fontSize": 11,
        "textVertical": false,
        "noBorder": false,
        "groupId": null
      },
      {
        "id": "item-n5dvwm4b",
        "type": "seat",
        "label": "",
        "x": 150,
        "y": 310,
        "w": 80,
        "h": 60,
        "r": 0,
        "status": "free",
        "assignedName": "",
        "note": "",
        "locked": false,
        "assignable": true,
        "assignableLocked": true,
        "color": "",
        "z": 47,
        "fontSize": 13,
        "textVertical": false,
        "noBorder": false,
        "groupId": null
      },
      {
        "id": "item-vivlcytr",
        "type": "seat",
        "label": "",
        "x": 150,
        "y": 375,
        "w": 80,
        "h": 60,
        "r": 0,
        "status": "free",
        "assignedName": "",
        "note": "",
        "locked": false,
        "assignable": true,
        "assignableLocked": true,
        "color": "",
        "z": 48,
        "fontSize": 13,
        "textVertical": false,
        "noBorder": false,
        "groupId": null
      },
      {
        "id": "item-8cmz1uo4",
        "type": "seat",
        "label": "",
        "x": 150,
        "y": 440,
        "w": 80,
        "h": 60,
        "r": 0,
        "status": "free",
        "assignedName": "",
        "note": "",
        "locked": false,
        "assignable": true,
        "assignableLocked": false,
        "color": "",
        "z": 49,
        "fontSize": 13,
        "textVertical": false,
        "noBorder": false,
        "groupId": null
      },
      {
        "id": "item-ico7wl6h",
        "type": "seat",
        "label": "",
        "x": 75,
        "y": 65,
        "w": 80,
        "h": 60,
        "r": 0,
        "status": "free",
        "assignedName": "",
        "note": "",
        "locked": false,
        "assignable": true,
        "assignableLocked": true,
        "color": "",
        "z": 50,
        "fontSize": 13,
        "textVertical": false,
        "noBorder": false,
        "groupId": null
      },
      {
        "id": "item-kkf48efj",
        "type": "seat",
        "label": "",
        "x": 75,
        "y": 130,
        "w": 80,
        "h": 60,
        "r": 0,
        "status": "free",
        "assignedName": "",
        "note": "",
        "locked": false,
        "assignable": true,
        "assignableLocked": true,
        "color": "",
        "z": 51,
        "fontSize": 13,
        "textVertical": false,
        "noBorder": false,
        "groupId": null
      },
      {
        "id": "item-vkming05",
        "type": "seat",
        "label": "",
        "x": 75,
        "y": 195,
        "w": 80,
        "h": 60,
        "r": 0,
        "status": "free",
        "assignedName": "",
        "note": "",
        "locked": false,
        "assignable": true,
        "assignableLocked": true,
        "color": "",
        "z": 52,
        "fontSize": 13,
        "textVertical": false,
        "noBorder": false,
        "groupId": null
      },
      {
        "id": "item-yi2fhiib",
        "type": "seat",
        "label": "",
        "x": 170,
        "y": 65,
        "w": 80,
        "h": 60,
        "r": 0,
        "status": "free",
        "assignedName": "",
        "note": "",
        "locked": false,
        "assignable": true,
        "assignableLocked": true,
        "color": "",
        "z": 53,
        "fontSize": 13,
        "textVertical": false,
        "noBorder": false,
        "groupId": null
      },
      {
        "id": "item-sckghgiw",
        "type": "seat",
        "label": "",
        "x": 170,
        "y": 130,
        "w": 80,
        "h": 60,
        "r": 0,
        "status": "free",
        "assignedName": "",
        "note": "",
        "locked": false,
        "assignable": true,
        "assignableLocked": true,
        "color": "",
        "z": 54,
        "fontSize": 13,
        "textVertical": false,
        "noBorder": false,
        "groupId": null
      },
      {
        "id": "item-lnselidv",
        "type": "seat",
        "label": "",
        "x": 170,
        "y": 195,
        "w": 80,
        "h": 60,
        "r": 0,
        "status": "free",
        "assignedName": "",
        "note": "",
        "locked": false,
        "assignable": true,
        "assignableLocked": true,
        "color": "",
        "z": 55,
        "fontSize": 13,
        "textVertical": false,
        "noBorder": false,
        "groupId": null
      },
      {
        "id": "item-8kus59ia",
        "type": "seat",
        "label": "",
        "x": 360,
        "y": 510,
        "w": 80,
        "h": 60,
        "r": 0,
        "status": "free",
        "assignedName": "",
        "note": "",
        "locked": false,
        "assignable": true,
        "assignableLocked": true,
        "color": "",
        "z": 56,
        "fontSize": 13,
        "textVertical": false,
        "noBorder": false,
        "groupId": null
      },
      {
        "id": "item-4kcmxud6",
        "type": "seat",
        "label": "",
        "x": 445,
        "y": 510,
        "w": 80,
        "h": 60,
        "r": 0,
        "status": "free",
        "assignedName": "",
        "note": "",
        "locked": false,
        "assignable": true,
        "assignableLocked": true,
        "color": "",
        "z": 57,
        "fontSize": 13,
        "textVertical": false,
        "noBorder": false,
        "groupId": null
      },
      {
        "id": "item-xt4swp5a",
        "type": "seat",
        "label": "",
        "x": 530,
        "y": 510,
        "w": 80,
        "h": 60,
        "r": 0,
        "status": "free",
        "assignedName": "",
        "note": "",
        "locked": false,
        "assignable": true,
        "assignableLocked": true,
        "color": "",
        "z": 58,
        "fontSize": 13,
        "textVertical": false,
        "noBorder": false,
        "groupId": null
      },
      {
        "id": "item-aszmarof",
        "type": "seat",
        "label": "",
        "x": 615,
        "y": 510,
        "w": 80,
        "h": 60,
        "r": 0,
        "status": "free",
        "assignedName": "",
        "note": "",
        "locked": false,
        "assignable": true,
        "assignableLocked": true,
        "color": "",
        "z": 59,
        "fontSize": 13,
        "textVertical": false,
        "noBorder": false,
        "groupId": null
      },
      {
        "id": "item-fqdii1q9",
        "type": "seat",
        "label": "",
        "x": 700,
        "y": 510,
        "w": 80,
        "h": 60,
        "r": 0,
        "status": "free",
        "assignedName": "",
        "note": "",
        "locked": false,
        "assignable": true,
        "assignableLocked": true,
        "color": "",
        "z": 60,
        "fontSize": 13,
        "textVertical": false,
        "noBorder": false,
        "groupId": null
      },
      {
        "id": "item-neukjeea",
        "type": "seat",
        "label": "",
        "x": 785,
        "y": 510,
        "w": 80,
        "h": 60,
        "r": 0,
        "status": "free",
        "assignedName": "",
        "note": "",
        "locked": false,
        "assignable": true,
        "assignableLocked": true,
        "color": "",
        "z": 61,
        "fontSize": 13,
        "textVertical": false,
        "noBorder": false,
        "groupId": null
      }
    ]
  }
}